odoo/addons/base_edifact/README.rst
odoo/addons/base_edifact/__init__.py
odoo/addons/base_edifact/__manifest__.py
odoo/addons/base_edifact/i18n/base_edifact.pot
odoo/addons/base_edifact/i18n/fr.po
odoo/addons/base_edifact/i18n/it.po
odoo/addons/base_edifact/models/__init__.py
odoo/addons/base_edifact/models/edifact.py
odoo/addons/base_edifact/readme/CONFIGURE.rst
odoo/addons/base_edifact/readme/CONTRIBUTORS.rst
odoo/addons/base_edifact/readme/DESCRIPTION.rst
odoo/addons/base_edifact/readme/HISTORY.rst
odoo/addons/base_edifact/readme/INSTALL.rst
odoo/addons/base_edifact/readme/USAGE.rst
odoo/addons/base_edifact/static/description/icon.png
odoo/addons/base_edifact/static/description/icon.svg
odoo/addons/base_edifact/static/description/index.html
odoo/addons/base_edifact/tests/__init__.py
odoo/addons/base_edifact/tests/test_base_edifact.py
odoo/addons/base_edifact/tests/files/Retail_EDIFACT_ORDERS_sample1.txt
odoo/addons/base_edifact/tests/files/Retail_EDIFACT_ORDERS_sample2.txt
odoo/addons/base_edifact/tests/files/test_orders_-_no_PRI_segments.txt
odoo/addons/base_edifact/tests/files/test_orders_-_no_ean_in_LIN_segments.txt
odoo_addon_base_edifact-16.0.1.5.1.dist-info/METADATA
odoo_addon_base_edifact-16.0.1.5.1.dist-info/WHEEL
odoo_addon_base_edifact-16.0.1.5.1.dist-info/top_level.txt
odoo_addon_base_edifact-16.0.1.5.1.dist-info/RECORD
