Metadata-Version: 2.1
Name: odoo-addon-base-edifact
Version: 16.0.1.5.1
Summary: UN/EDIFACT/D96A utilities using pydifact parser
Home-page: https://github.com/OCA/edi
Author: ALBA Software, PlanetaTIC, Odoo Community Association (OCA)
Author-email: support@odoo-community.org
License: AGPL-3
Platform: UNKNOWN
Classifier: Programming Language :: Python
Classifier: Framework :: Odoo
Classifier: Framework :: Odoo :: 16.0
Classifier: License :: OSI Approved :: GNU Affero General Public License v3
Classifier: Development Status :: 3 - Alpha
Requires-Python: >=3.10
Requires-Dist: odoo-addon-partner-identification <16.1dev,>=16.0dev
Requires-Dist: odoo-addon-partner-identification-gln <16.1dev,>=16.0dev
Requires-Dist: odoo <16.1dev,>=16.0a
Requires-Dist: pydifact
